LICENSE.MIT
MANIFEST.in
README.rst
setup.cfg
setup.py
src/admin_helpers.py
src/django_model_admin_helper.egg-info/PKG-INFO
src/django_model_admin_helper.egg-info/SOURCES.txt
src/django_model_admin_helper.egg-info/dependency_links.txt
src/django_model_admin_helper.egg-info/not-zip-safe
src/django_model_admin_helper.egg-info/requires.txt
src/django_model_admin_helper.egg-info/top_level.txt