Metadata-Version: 1.1
Name: django-model-admin-helper
Version: 0.1
Summary: Admin helpers
Home-page: http://github.com/Arpaso/django-model-admin-helper
Author: Arpaso
Author-email: arvid@arpaso.com
License: UNKNOWN
Download-URL: http://github.com/Arpaso/django-model-admin-helper/tarball/0.1
Platform: UNKNOWN
Classifier: Framework :: Django
Classifier: Intended Audience :: Developers
Classifier: Intended Audience :: System Administrators
Classifier: Operating System :: OS Independent
Classifier: Topic :: Software Development
